Workbook

Sheet 07 2024
A1: S-TEC SYSTEM VINA CO.,LTD
A2: Add: 14th Floor Sao Mai Building, 19 Le Van Luong, Nhan Chinh Ward, Thanh Xuan District, Ha Noi
G3: BẢNG THANH TOÁN TIỀN LƯƠNG
E4: Working day: | F4: 23 | G4: Tháng 07 năm 2024
A5: No. | B5: 성명 / NAME | C5: Mã số thuế cá nhân | D5: CMT/ CCCD | E5: 기본급여 | F5: 근무일수/nngày làm việc | G5: 적용 급여/Tiền lương thực tế | H5: 식대/Tiền ăn | I5: Điện thoại | J5: Xăng xe | K5: Lương chất lượng hiệu quả công việc | L5: 급여총계/Thu nhập trước thuế | M5: Thu nhập chịu thuế | N5: Giảm trừ bản thân | O5: 부양가족수/Số người phụ thuộc | P5: 소득세기준자료/Tiền lương tính thuế TNCN | Q5: 소득세/Thuế TNCN | R5: /BH- phần Công ty đóng | S5: 보험/BH người LĐ đóng | T5: 실수령액/Thực lĩnh | U5: 비고/Ghi chú | V5: 서명
B6: 직종 JOB TITLE | E6: BASIC SALARY | F6: WORKING DAY | G6: ACTUAL SALARY (1) | H6: MEAL (3) | I6: MOBILE PHONE (4) | J6: Oil(5) | K6: KPI(6) | L6: GROSS AMOUNT (7)= (1)+(2)+(3)+(4)+(5)+(6) | M6: TAXABLE INCOME | N6: Deduct | O6: QTY PERSON BELONG TO | P6: INCOME PAYABLE | Q6: PIT (8) | R6: INSURANCE- Company (9) | S6: INSURANCE- staff (10) | T6: NET TAKE HOME (11)=(7)-(8)-(10) | U6: REMARKS | V6: SIGNATURE
B7: CHOI JONG KOOK | G7: =+E7*F7/$F$4 -> 0 | H7: =E3*F7 -> 0 | L7: =SUM(G7:K7) -> 0 | M7: =(L7-H7-I7) -> 0 | O7: 0 | P7: =IF(M7-N7-O7*4400000-S7<0,0,M7-N7-O7*4400000-S7) -> 0 | Q7: =IF(P7<=5000000,P7*5%,IF(P7<=10000000,P7*10%-250000,IF(P7<=18000000,P7*15%-750000,IF(P7<=32000000,P7*20%-1650000,IF(P7<=52000000,P7*25%-3250000,IF(P7<=80000000,P7*30%-5850000)))))) -> 0 | T7: =ROUND(L7-Q7-S7,-3) -> 0
A8: 1 | B8: CHÚC LÊ NGỌC | E8: =12987000*85% -> 11038950 | F8: 3 | G8: =+E8*F8/$F$4 -> 1439863 | H8: =35000*F8 -> 105000 | L8: =SUM(G8:K8) -> 1544863 | M8: =(L8-H8-I8) -> 1439863 | N8: 11000000 | O8: 4400000 | P8: =IF(M8-N8-O8*4400000-S8<0,0,M8-N8-O8*4400000-S8) -> 0 | Q8: =IF(P8<=5000000,P8*5%,IF(P8<=10000000,P8*10%-250000,IF(P8<=18000000,P8*15%-750000,IF(P8<=32000000,P8*20%-1650000,IF(P8<=52000000,P8*25%-3250000,IF(P8<=80000000,P8*30%-5850000)))))) -> 0 | T8: =ROUND(L8-Q8-S8,-3) -> 1545000
A9: 2 | B9: NGUYỄN THANH NGA | E9: =20000000*85% -> 17000000 | F9: 8 | G9: =+E9*F9/$F$4 -> 5913043.5 | H9: =35000*F9 -> 280000 | L9: =SUM(G9:K9) -> 6193043.5 | M9: =(L9-H9-I9) -> 5913043.5 | N9: 11000000 | O9: 4400000 | P9: =IF(M9-N9-O9*4400000-S9<0,0,M9-N9-O9*4400000-S9) -> 0 | Q9: =IF(P9<=5000000,P9*5%,IF(P9<=10000000,P9*10%-250000,IF(P9<=18000000,P9*15%-750000,IF(P9<=32000000,P9*20%-1650000,IF(P9<=52000000,P9*25%-3250000,IF(P9<=80000000,P9*30%-5850000)))))) -> 0 | T9: =ROUND(L9-Q9-S9,-3) -> 6193000
A10: 3 | B10: TRẦN MINH HOÀNG | E10: 5000000 | F10: 13 | G10: =+E10*F10/$F$4 -> 2826087 | H10: =35000*F10 -> 455000 | L10: =SUM(G10:K10) -> 3281087 | M10: =(L10-H10-I10) -> 2826087 | N10: 11000000 | P10: =IF(M10-N10-O10*4400000-S10<0,0,M10-N10-O10*4400000-S10) -> 0 | Q10: =IF(P10<=5000000,P10*5%,IF(P10<=10000000,P10*10%-250000,IF(P10<=18000000,P10*15%-750000,IF(P10<=32000000,P10*20%-1650000,IF(P10<=52000000,P10*25%-3250000,IF(P10<=80000000,P10*30%-5850000)))))) -> 0 | T10: =ROUND(L10-Q10-S10,-3) -> 3281000
A11: 개인별 소계 SUB TOTAL | E11: =SUM(E7:E10) -> 33038950 | F11: =SUM(F7:F10) -> 24 | G11: =SUM(G7:G10) -> 10178993 | H11: =SUM(H7:H10) -> 840000 | I11: =SUM(I7:I10) -> 0 | J11: =SUM(J7:J10) -> 0 | K11: =SUM(K7:K10) -> 0 | L11: =SUM(L7:L10) -> 11018993 | ... T11: =SUM(T7:T10) -> 11019000
B13: Người lập biểu | I13: Người phê duyệt | S13: Giám đốc

Sheet Tong hop
B3: STT/ Number | C3: Họ tện (Name) | D3: Loại Hợp đồng (Type labor contract) | E3: Loại Hợp đồng (Status) | F3: Lương thực lĩnh/Net Payment | G3: Thuế TNCN- Công ty đóng | H3: BHXH- Công ty đóng
B4: 1 | C4: Đoàn Ngọc Anh | D4: Toàn thời gian | E4: NET | F4: =SALARY!L5 -> 5000000 | G4: =SALARY!R5 -> 277777.78 | H4: =SALARY!S5+SALARY!T5 -> 0
B5: 2 | C5: Tạ Trường Xuân | D5: Toàn thời gian | E5: NET | F5: =SALARY!L6 -> 20000000 | G5: =SALARY!R6 -> 242105.26 | H5: =SALARY!S6+SALARY!T6 -> 6400000
B6: 3 | C6: Chu Văn Hiếu | D6: Toàn thời gian | E6: NET | F6: =SALARY!L7 -> 10000000 | G6: =SALARY!R7 -> 0 | H6: =SALARY!S7+SALARY!T7 -> 3200000
B7: 4 | C7: Nguyễn Văn Hòa | D7: Toàn thời gian | E7: NET | F7: =SALARY!L8 -> 12000000 | G7: =SALARY!R8 -> 1050000 | H7: =SALARY!S8+SALARY!T8 -> 0
B8: 5 | C8: Nguyễn Ngọc Hà | D8: Toàn thời gian | E8: NET | F8: =SALARY!L9 -> 6800000 | G8: =SALARY!R9 -> 0 | H8: =SALARY!S9+SALARY!T9 -> 0
B9: 6 | C9: Lê Quang Huy | D9: Toàn thời gian | E9: NET | F9: =SALARY!L10 -> 7727273 | G9: =SALARY!R10 -> 0 | H9: =SALARY!S10+SALARY!T10 -> 0
B11: 7 | C11: Lưu Đức Hà | D11: Bán thời gian | E11: NET | F11: =SALARY!L12 -> 10000000 | G11: =SALARY!R12 -> 1111111 | H11: =SALARY!S12+SALARY!T12 -> 0
B12: 8 | C12: Phan Thị Nhài | D12: Bán thời gian | E12: NET | F12: =SALARY!L13 -> 3000000 | G12: =SALARY!R13 -> 333333 | H12: =SALARY!S13+SALARY!T13 -> 0
B13: 9 | C13: Vũ Văn Tiến Tuyền | D13: Bán thời gian | E13: NET | F13: =SALARY!L14 -> 10000000 | G13: =SALARY!R14 -> 1111111 | H13: =SALARY!S14+SALARY!T14 -> 0
B14: 10 | C14: Koshioka Hiroshi | D14: Bán thời gian | E14: NET | F14: =SALARY!L15 -> 3000000 | G14: =SALARY!R15 -> 333333 | H14: =SALARY!S15+SALARY!T15 -> 0
C16: TOTAL | F16: =SUM(F4:F15) -> 87527273 | G16: =SUM(G4:G15) -> 4458771 | H16: =SUM(H4:H15) -> 9600000

Sheet SALARY
I1: BẢNG THANH TOÁN TIỀN LƯƠNG/ Salary table
I2: Tháng 05 năm 2025/ May, 2025
E3: Số ngày làm việc chuẩn/Standard working day | H3: 22 | N3: 4400000 | S3: 0.215 | T3: 0.105
A4: STT/ Number | B4: Họ tện (Name) | C4: Loại Hợp đồng (Type labor contract) | D4: Loại Hợp đồng (Status) | E4: Hệ số lương/ salary coefficient) | F4: Lương ngày công/Working day salary | G4: Lương đóng BHXH/ Insurance salary | H4: Số ngày làm việc (Days) | I4: Lương thực tế/Actual salary | J4: Ăn ca/Meal | K4: Điện thoại/Tel | L4: Lương thực lĩnh/Net Payment | M4: Giảm trừ bản thân/Employee Deduction | N4: Số người phụ thuộc/Dependent | O4: Tổng các khoản giảm trừ/Total Deduction | P4: Thu nhập làm căn cứ quy đổi/Assessible income | Q4: Thu nhập tính thuế/Taxable income | R4: Thuế TNCN/PIT | S4: Bảo hiểm công ty trả/ insurance_ Employer | T4: Bảo hiểm NLĐ trả/ insurance_ Employee | U4: Thực lĩnh/Net income | V4: Thu nhập chịu thuế | W4: MST cá nhân/Tax code | Y4: Check
A5: 1 | B5: Đoàn Ngọc Anh | C5: Toàn thời gian | D5: NET | E5: 1 | F5: 5000000 | H5: 22 | I5: =ROUND(F5*E5/$H$3*H5,0) -> 5000000 | J5: 0 | K5: 0 | L5: =SUM(I5:K5) -> 5000000 | O5: =M5+$N$3*N5 -> 0 | P5: =IF(L5-O5>0,L5-O5,0) -> 5000000 | Q5: =IF(P5>0,IF(P5<=4750000,(P5/0.95),IF(P5<=9250000,(P5-250000)/0.9,IF(P5<=16050000,(P5-750000)/0.85,IF(P5<=27250000,(P5-1650000)/0.8,IF(P5<=42250000,(P5-3250000)/0.75,IF(P5<=61850000,(P5-5850000)/0.7,IF(P5>61850000,(P5-9850000)/0.65,0))))))),0) -> 5277777.8 | R5: =IF(Q5>80000000,Q5*35%-9850000,IF(Q5>52000000,Q5*30%-5850000,IF(Q5>32000000,Q5*25%-3250000,IF(Q5>18000000,Q5*20%-1650000,IF(Q5>10000000,Q5*15%-750000,IF(Q5>5000000,Q5*10%-250000,IF(AND(Q5<=5000000,Q5>0),Q5*5%,0))))))) -> 277777.78 | S5: =ROUND(G5*$S$3,0) -> 0 | T5: =ROUND(G5*$T$3,0) -> 0 | U5: =I5 -> 5000000 | V5: =L5+R5+T5 -> 5277777.8 | X5: =IF(Q5>0,Q5+O5+T5,L5+T5) -> 5277777.8 | Y5: =X5-V5 -> 0
A6: 2 | B6: Tạ Trường Xuân | C6: Toàn thời gian | D6: NET | E6: 1 | F6: 20000000 | G6: 20000000 | H6: 22 | I6: =ROUND(F6*E6/$H$3*H6,0) -> 20000000 | J6: 0 | K6: 0 | L6: =SUM(I6:K6) -> 20000000 | M6: 11000000 | N6: 1 | O6: =M6+$N$3*N6 -> 15400000 | P6: =IF(L6-O6>0,L6-O6,0) -> 4600000 | Q6: =IF(P6>0,IF(P6<=4750000,(P6/0.95),IF(P6<=9250000,(P6-250000)/0.9,IF(P6<=16050000,(P6-750000)/0.85,IF(P6<=27250000,(P6-1650000)/0.8,IF(P6<=42250000,(P6-3250000)/0.75,IF(P6<=61850000,(P6-5850000)/0.7,IF(P6>61850000,(P6-9850000)/0.65,0))))))),0) -> 4842105.3 | R6: =IF(Q6>80000000,Q6*35%-9850000,IF(Q6>52000000,Q6*30%-5850000,IF(Q6>32000000,Q6*25%-3250000,IF(Q6>18000000,Q6*20%-1650000,IF(Q6>10000000,Q6*15%-750000,IF(Q6>5000000,Q6*10%-250000,IF(AND(Q6<=5000000,Q6>0),Q6*5%,0))))))) -> 242105.26 | S6: =ROUND(G6*$S$3,0) -> 4300000 | T6: =ROUND(G6*$T$3,0) -> 2100000 | U6: =I6 -> 20000000 | V6: =L6+R6+T6 -> 22342105 | X6: =IF(Q6>0,Q6+O6+T6,L6+T6) -> 22342105 | Y6: =X6-V6 -> 0
A7: 3 | B7: Chu Văn Hiếu | C7: Toàn thời gian | D7: NET | E7: 1 | F7: 10000000 | G7: 10000000 | H7: 22 | I7: =ROUND(F7*E7/$H$3*H7,0) -> 10000000 | J7: 0 | K7: 0 | L7: =SUM(I7:K7) -> 10000000 | M7: 11000000 | O7: =M7+$N$3*N7 -> 11000000 | P7: =IF(L7-O7>0,L7-O7,0) -> 0 | Q7: =IF(P7>0,IF(P7<=4750000,(P7/0.95),IF(P7<=9250000,(P7-250000)/0.9,IF(P7<=16050000,(P7-750000)/0.85,IF(P7<=27250000,(P7-1650000)/0.8,IF(P7<=42250000,(P7-3250000)/0.75,IF(P7<=61850000,(P7-5850000)/0.7,IF(P7>61850000,(P7-9850000)/0.65,0))))))),0) -> 0 | R7: =IF(Q7>80000000,Q7*35%-9850000,IF(Q7>52000000,Q7*30%-5850000,IF(Q7>32000000,Q7*25%-3250000,IF(Q7>18000000,Q7*20%-1650000,IF(Q7>10000000,Q7*15%-750000,IF(Q7>5000000,Q7*10%-250000,IF(AND(Q7<=5000000,Q7>0),Q7*5%,0))))))) -> 0 | S7: =ROUND(G7*$S$3,0) -> 2150000 | T7: =ROUND(G7*$T$3,0) -> 1050000 | U7: =I7 -> 10000000 | V7: =L7+R7+T7 -> 11050000 | X7: =IF(Q7>0,Q7+O7+T7,L7+T7) -> 11050000 | Y7: =X7-V7 -> 0
A8: 4 | B8: Nguyễn Văn Hòa | C8: Toàn thời gian | D8: GROSS | E8: 1 | F8: 12000000 | H8: 22 | I8: =ROUND(F8*E8/$H$3*H8,0) -> 12000000 | J8: 0 | K8: 0 | L8: =SUM(I8:K8) -> 12000000 | O8: =M8+$N$3*N8 -> 0 | P8: =IF(L8-O8>0,L8-O8,0) -> 12000000 | Q8: =P8 -> 12000000 | R8: =IF(Q8>80000000,Q8*35%-9850000,IF(Q8>52000000,Q8*30%-5850000,IF(Q8>32000000,Q8*25%-3250000,IF(Q8>18000000,Q8*20%-1650000,IF(Q8>10000000,Q8*15%-750000,IF(Q8>5000000,Q8*10%-250000,IF(AND(Q8<=5000000,Q8>0),Q8*5%,0))))))) -> 1050000 | S8: =ROUND(G8*$S$3,0) -> 0 | T8: =ROUND(G8*$T$3,0) -> 0 | U8: =I8-R8 -> 10950000 | V8: =Q8 -> 12000000 | X8: =IF(Q8>0,Q8+O8+T8,L8+T8) -> 12000000 | Y8: =X8-V8 -> 0
A9: 5 | B9: Nguyễn Ngọc Hà | C9: Toàn thời gian | D9: NET | E9: 0.85 | F9: 8000000 | H9: 22 | I9: =ROUND(F9*E9/$H$3*H9,0) -> 6800000 | J9: 0 | K9: 0 | L9: =SUM(I9:K9) -> 6800000 | M9: 11000000 | O9: =M9+$N$3*N9 -> 11000000 | P9: =IF(L9-O9>0,L9-O9,0) -> 0 | Q9: =IF(P9>0,IF(P9<=4750000,(P9/0.95),IF(P9<=9250000,(P9-250000)/0.9,IF(P9<=16050000,(P9-750000)/0.85,IF(P9<=27250000,(P9-1650000)/0.8,IF(P9<=42250000,(P9-3250000)/0.75,IF(P9<=61850000,(P9-5850000)/0.7,IF(P9>61850000,(P9-9850000)/0.65,0))))))),0) -> 0 | R9: =IF(Q9>80000000,Q9*35%-9850000,IF(Q9>52000000,Q9*30%-5850000,IF(Q9>32000000,Q9*25%-3250000,IF(Q9>18000000,Q9*20%-1650000,IF(Q9>10000000,Q9*15%-750000,IF(Q9>5000000,Q9*10%-250000,IF(AND(Q9<=5000000,Q9>0),Q9*5%,0))))))) -> 0 | S9: =ROUND(G9*$S$3,0) -> 0 | T9: =ROUND(G9*$T$3,0) -> 0 | U9: =I9 -> 6800000 | V9: =L9+R9+T9 -> 6800000 | W9: 8761030932 | X9: =IF(Q9>0,Q9+O9+T9,L9+T9) -> 6800000 | Y9: =X9-V9 -> 0
A10: 6 | B10: Lê Quang Huy | C10: Toàn thời gian | D10: NET | E10: 0.85 | F10: 10000000 | H10: 20 | I10: =ROUND(F10*E10/$H$3*H10,0) -> 7727273 | J10: 0 | K10: 0 | L10: =SUM(I10:K10) -> 7727273 | M10: 11000000 | O10: =M10+$N$3*N10 -> 11000000 | P10: =IF(L10-O10>0,L10-O10,0) -> 0 | Q10: =IF(P10>0,IF(P10<=4750000,(P10/0.95),IF(P10<=9250000,(P10-250000)/0.9,IF(P10<=16050000,(P10-750000)/0.85,IF(P10<=27250000,(P10-1650000)/0.8,IF(P10<=42250000,(P10-3250000)/0.75,IF(P10<=61850000,(P10-5850000)/0.7,IF(P10>61850000,(P10-9850000)/0.65,0))))))),0) -> 0 | R10: =IF(Q10>80000000,Q10*35%-9850000,IF(Q10>52000000,Q10*30%-5850000,IF(Q10>32000000,Q10*25%-3250000,IF(Q10>18000000,Q10*20%-1650000,IF(Q10>10000000,Q10*15%-750000,IF(Q10>5000000,Q10*10%-250000,IF(AND(Q10<=5000000,Q10>0),Q10*5%,0))))))) -> 0 | S10: =ROUND(G10*$S$3,0) -> 0 | T10: =ROUND(G10*$T$3,0) -> 0 | U10: =I10 -> 7727273 | V10: =L10+R10+T10 -> 7727273 | W10: 8599443547 | X10: =IF(Q10>0,Q10+O10+T10,L10+T10) -> 7727273 | Y10: =X10-V10 -> 0
I11: =SUM(I5:I10) -> 61527273
A12: 7 | B12: Lưu Đức Hà | C12: Bán thời gian | D12: NET | E12: 1 | F12: 10000000 | H12: 22 | I12: =ROUND(F12*E12/$H$3*H12,0) -> 10000000 | J12: 0 | K12: 0 | L12: =SUM(I12:K12) -> 10000000 | O12: =M12+$N$3*N12 -> 0 | P12: =IF(L12-O12>0,L12-O12,0) -> 10000000 | Q12: =ROUND(P12/0.9,0) -> 11111111 | R12: =ROUND(Q12*0.1,0) -> 1111111 | S12: =ROUND(G12*$S$3,0) -> 0 | T12: =ROUND(G12*$T$3,0) -> 0 | U12: =I12 -> 10000000
A13: 8 | B13: Phan Thị Nhài | C13: Bán thời gian | D13: NET | E13: 1 | F13: 3000000 | H13: 22 | I13: =ROUND(F13*E13/$H$3*H13,0) -> 3000000 | J13: 0 | K13: 0 | L13: =SUM(I13:K13) -> 3000000 | O13: =M13+$N$3*N13 -> 0 | P13: =IF(L13-O13>0,L13-O13,0) -> 3000000 | Q13: =ROUND(P13/0.9,0) -> 3333333 | R13: =ROUND(Q13*0.1,0) -> 333333 | S13: =ROUND(G13*$S$3,0) -> 0 | T13: =ROUND(G13*$T$3,0) -> 0 | U13: =I13 -> 3000000
A14: 9 | B14: Vũ Văn Tiến Tuyền | C14: Bán thời gian | D14: NET | E14: 1 | F14: 10000000 | H14: 22 | I14: =ROUND(F14*E14/$H$3*H14,0) -> 10000000 | J14: 0 | K14: 0 | L14: =SUM(I14:K14) -> 10000000 | O14: =M14+$N$3*N14 -> 0 | P14: =IF(L14-O14>0,L14-O14,0) -> 10000000 | Q14: =ROUND(P14/0.9,0) -> 11111111 | R14: =ROUND(Q14*0.1,0) -> 1111111 | S14: =ROUND(G14*$S$3,0) -> 0 | T14: =ROUND(G14*$T$3,0) -> 0 | U14: =I14 -> 10000000
A15: 10 | B15: Koshioka Hiroshi | C15: Bán thời gian | D15: NET | E15: 1 | F15: 3000000 | H15: 22 | I15: =ROUND(F15*E15/$H$3*H15,0) -> 3000000 | J15: 0 | K15: 0 | L15: =SUM(I15:K15) -> 3000000 | O15: =M15+$N$3*N15 -> 0 | P15: =IF(L15-O15>0,L15-O15,0) -> 3000000 | Q15: =ROUND(P15/0.9,0) -> 3333333 | R15: =ROUND(Q15*0.1,0) -> 333333 | S15: =ROUND(G15*$S$3,0) -> 0 | T15: =ROUND(G15*$T$3,0) -> 0 | U15: =I15 -> 3000000 | W15: Đăng ký MST từ tháng 5
A17: TỔNG CỘNG/Total | F17: =SUM(F5:F16) -> 91000000 | H17: =SUM(H5:H16) -> 218 | I17: =SUM(I5:I16) -> 149054546 | J17: =SUM(J5:J16) -> 0 | K17: =SUM(K5:K16) -> 0 | L17: =SUM(L5:L16) -> 87527273 | R17: =SUM(R5:R16) -> 4458771 | S17: =SUM(S5:S16) -> 6450000 | T17: =SUM(T5:T16) -> 3150000 | U17: =SUM(U5:U16) -> 86477273
K19: Ngày 31 tháng 05 năm 2025
B20: Người lập biểu/Maker | K20: Giám đốc/CEO

Sheet INSURANCE
C1: BẢNG TÍNH BẢO HIỂM/INSURANCE
F2: Tháng 05 năm 2025
A4: STT | B4: Họ tên | C4: Lương cơ bản | D4: BH Công ty đóng (21.5%) | H4: BH người LĐ đóng (10.5%) | L4: Tổng cộng | M4: REMARK
D5: BHXH (17.5%) | E5: BHYT (3%) | F5: BHTN (1%) | G5: Tổng | H5: BHXH (8%) | I5: BHYT (1.5%) | J5: BHTN (1%) | K5: Tổng
A6: 1 | B6: Tạ Trường Xuân | C6: 20000000 | D6: =C6*17.5% -> 3500000 | E6: =C6*3% -> 600000 | F6: =C6*1% -> 200000 | G6: =SUM(D6:F6) -> 4300000 | H6: =C6*8% -> 1600000 | I6: =C6*1.5% -> 300000 | J6: =C6*1% -> 200000 | K6: =SUM(H6:J6) -> 2100000 | L6: =K6+G6 -> 6400000
A7: 2 | B7: Chu Văn Hiếu | C7: 10000000 | D7: =C7*17.5% -> 1750000 | E7: =C7*3% -> 300000 | F7: =C7*1% -> 100000 | G7: =SUM(D7:F7) -> 2150000 | H7: =C7*8% -> 800000 | I7: =C7*1.5% -> 150000 | J7: =C7*1% -> 100000 | K7: =SUM(H7:J7) -> 1050000 | L7: =K7+G7 -> 3200000
A10: TOTAL | C10: =SUM(C6:C9) -> 30000000 | D10: =SUM(D6:D9) -> 5250000 | E10: =SUM(E6:E9) -> 900000 | F10: =SUM(F6:F9) -> 300000 | G10: =SUM(G6:G9) -> 6450000 | H10: =SUM(H6:H9) -> 2400000 | I10: =SUM(I6:I9) -> 450000 | J10: =SUM(J6:J9) -> 300000 | ... L10: =SUM(L6:L9) -> 9600000
B13: Người lập biểu | F13: Giám đốc
